Metadata-Version: 2.1
Name: PydeequDynamicParser
Version: 0.3
Summary: Python library which makes it possible to use validation rules in pydeequ based on json structures.
Home-page: https://github.com/wesleywilian/pydeequ-dynamic-parser
Author: wesleywilian
License: apache-2.0
Download-URL: https://github.com/wesleywilian/pydeequ-dynamic-parser/archive/v0.3.tar.gz
Keywords: pydeequ,json,data,quality,rules
Platform: UNKNOWN
Classifier: Development Status :: 3 - Alpha
Classifier: Intended Audience :: Developers
Classifier: Topic :: Software Development :: Build Tools
Classifier: License :: OSI Approved :: Apache Software License
Classifier: Programming Language :: Python :: 3
Classifier: Programming Language :: Python :: 3.7
Classifier: Programming Language :: Python :: 3.8
Classifier: Programming Language :: Python :: 3.9
License-File: LICENSE
